textcaret/__init__.py
textcaret/functions/__init__.py
textcaret/functions/functions.py
textcaret/textcaret.py
textcaret-0.0.1.dist-info/WHEEL
textcaret-0.0.1.dist-info/METADATA
textcaret-0.0.1.dist-info/RECORD
