Metadata-Version: 2.1
Name: textcaret
Version: 0.0.1
Summary: Simplified NLP Toolkit for unifying common Natural Language Processing Tasks
Home-page: https://github.com/jcharistech/textcaret
License: MIT
Keywords: textcaret,tidytext,jcharistech,pycaret,NLP,text preprocessing,text vizualization,text summarization,sweetviz,pandas,sumy,normalize,textblob
Author: Jesse E.Agbe(JCharis)
Author-email: jcharistech@gmail.com
Requires-Python: >=3.8,<4.0
Classifier: License :: OSI Approved :: MIT License
Classifier: Operating System :: OS Independent
Classifier: Programming Language :: Python :: 3
Classifier: Programming Language :: Python :: 3.6
Classifier: Programming Language :: Python :: 3.7
Classifier: Programming Language :: Python :: 3.8
Classifier: Programming Language :: Python :: 3.9
Requires-Dist: matplotlib (>=3.4.2,<4.0.0)
Requires-Dist: neattext (>=0.1.0,<0.2.0)
Requires-Dist: nltk (>=3.6.2,<4.0.0)
Requires-Dist: spacy (>=3.1.1,<4.0.0)
Requires-Dist: sumy (>=0.8.1,<0.9.0)
Requires-Dist: textblob (>=0.15.3,<0.16.0)
Requires-Dist: textstat (>=0.7.1,<0.8.0)
Requires-Dist: wordcloud (>=1.8.1,<2.0.0)
Project-URL: Repository, https://github.com/jcharistech/textcaret
